linear_garage_door/__init__.py
linear_garage_door/_util.py
linear_garage_door/const.py
linear_garage_door/errors.py
linear_garage_door/py.typed
linear_garage_door-0.2.10.dist-info/LICENSE
linear_garage_door-0.2.10.dist-info/METADATA
linear_garage_door-0.2.10.dist-info/WHEEL
linear_garage_door-0.2.10.dist-info/RECORD
