Metadata-Version: 2.1
Name: linear-garage-door
Version: 0.2.10
Summary: Control Linear Garage Doors with Python
Home-page: https://IceBotYT.github.io/linear-garage-door
License: MIT
Author: IceBotYT
Author-email: icebotyt@outlook.com
Requires-Python: >=3.8,<4.0
Classifier: Development Status :: 4 - Beta
Classifier: Intended Audience :: Developers
Classifier: License :: OSI Approved :: MIT License
Classifier: Operating System :: OS Independent
Classifier: Programming Language :: Python
Classifier: Programming Language :: Python :: 3
Classifier: Programming Language :: Python :: 3.8
Classifier: Programming Language :: Python :: 3.9
Classifier: Programming Language :: Python :: 3.10
Classifier: Programming Language :: Python :: 3.11
Classifier: Programming Language :: Python :: 3.12
Classifier: Programming Language :: Python :: 3.7
Classifier: Topic :: Software Development :: Libraries :: Python Modules
Classifier: Typing :: Typed
Requires-Dist: aiohttp (>=3.8.1,<4.0.0)
Requires-Dist: dnspython (>=2.3.0,<3.0.0)
Requires-Dist: tenacity (>=8.2.3,<9.0.0)
Project-URL: Documentation, https://IceBotYT.github.io/linear-garage-door
Project-URL: Repository, https://github.com/IceBotYT/linear-garage-door
